{
  "米尔网": {
    "header": {
      "Connection": "keep-alive",
      "Cache-Control": "max-age=0",
      "sec-ch-ua": "'Chromium';v='92', ' Not A;Brand';v='99', 'Google Chrome';v='92'",
      "sec-ch-ua-mobile": ",?0",
      "Upgrade-Insecure-Requests": "1",
      "User-Agent": "Mozilla/5.0 (Windows NT 10.0; Win64; x64) AppleWebKit/537.36 (KHTML, like Gecko) Chrome/92.0.4515.131 Safari/537.36",
      "Accept": "text/html,application/xhtml+xml,application/xml;q=0.9,image/avif,image/webp,image/apng,*/*;q=0.8,application/signed-exchange;v=b3;q=0.9",
      "Sec-Fetch-Site": "same-origin",
      "Sec-Fetch-Mode": "navigate",
      "Sec-Fetch-User": "?1",
      "Sec-Fetch-Dest": "document",
      "Accept-Language": "zh,en-GB;q=0.9,en-US;q=0.8,en;q=0.7,zh-CN;q=0.6"
    },
    "search_url": "http://military.miercn.com/zbs/getDatanew?type=1&page={}"
  },
  "豆瓣": {
    "header": {
      "Connection": "keep-alive",
      "Cache-Control": "max-age=0",
      "sec-ch-ua": "'Chromium';v='92', ' Not A;Brand';v='99', 'Google Chrome';v='92'",
      "sec-ch-ua-mobile": ",?0",
      "Upgrade-Insecure-Requests": "1",
      "User-Agent": "Mozilla/5.0 (Windows NT 10.0; Win64; x64) AppleWebKit/537.36 (KHTML, like Gecko) Chrome/92.0.4515.131 Safari/537.36",
      "Accept": "text/html,application/xhtml+xml,application/xml;q=0.9,image/avif,image/webp,image/apng,*/*;q=0.8,application/signed-exchange;v=b3;q=0.9",
      "Sec-Fetch-Site": "same-origin",
      "Sec-Fetch-Mode": "navigate",
      "Sec-Fetch-User": "?1",
      "Sec-Fetch-Dest": "document",
      "Accept-Language": "zh,en-GB;q=0.9,en-US;q=0.8,en;q=0.7,zh-CN;q=0.6"
    },
    "hot_url": "",
    "search_url": "https://movie.douban.com/review/latest/?start={}"
  },
  "大众点评": {
    "search_url": "https://www.maoyan.com/films?utm_source=dianpingweb",
    "header": {
      "Accept": "text/html,application/xhtml+xml,application/xml;q=0.9,image/avif,image/webp,image/apng,*/*;q=0.8,application/signed-exchange;v=b3;q=0.9",
      "Accept-Encoding": "gzip, deflate, br",
      "Accept-Language": "zh-CN,zh;q=0.9",
      "Cache-Control": "max-age=0",
      "Connection": "keep-alive",
      "Cookie": "uuid_n_v=v1; uuid=AACDDA50149A11EDAE417F96F78B36A046C2F043C0D94FEEBA34DB6D7AC94C28; _lxsdk_cuid=1826d2c7029c8-02460e5c0736c1-26021a51-144000-1826d2c7029c8; _lxsdk=AACDDA50149A11EDAE417F96F78B36A046C2F043C0D94FEEBA34DB6D7AC94C28; _csrf=f894eb215e413ed10f824d47338c2c66699711b6c3756e774fe5874d0a750fba; _lx_utm=utm_source%3Ddianpingweb; Hm_lvt_703e94591e87be68cc8da0da7cbd0be2=1659689005,1659689324; Hm_lpvt_703e94591e87be68cc8da0da7cbd0be2=1659689324; __mta=242455869.1659689005462.1659689124369.1659689324396.9; _lxsdk_s=1826d2c702d-221-984-dcf%7C%7C24",
      "Host": "www.maoyan.com",
      "sec-ch-ua": "'.Not/A)Brand';v='99', 'Google Chrome';v='103', 'Chromium';v='103'",
      "sec-ch-ua-mobile": "?0",
      "sec-ch-ua-platform": "'Windows'",
      "Sec-Fetch-Dest": "document",
      "Sec-Fetch-Mode": "navigate",
      "Sec-Fetch-Site": "none",
      "Sec-Fetch-User": "?1",
      "Upgrade-Insecure-Requests": "1",
      "User-Agent": "Mozilla/5.0 (Windows NT 10.0; Win64; x64) AppleWebKit/537.36 (KHTML, like Gecko) Chrome/103.0.0.0 Safari/537.36"
    }
  },
  "百度": {
    "header": {
      "Accept": "text/html,application/xhtml+xml,application/xml;q=0.9,image/avif,image/webp,image/apng,*/*;q=0.8,application/signed-exchange;v=b3;q=0.9",
      "Accept-Language": "zh-CN,zh;q=0.9",
      "Cache-Control": "max-age=0",
      "Connection": "keep-alive",
      "Sec-Fetch-Dest": "document",
      "Sec-Fetch-Mode": "navigate",
      "Sec-Fetch-Site": "same-origin",
      "Sec-Fetch-User": "?1",
      "Upgrade-Insecure-Requests": "1",
      "User-Agent": "Mozilla/5.0 (Windows NT 10.0; Win64; x64) AppleWebKit/537.36 (KHTML, like Gecko) Chrome/100.0.4896.127 Safari/537.36",
      "sec-ch-ua": "' Not A;Brand';v='99', 'Chromium';v='100', 'Google Chrome';v='100'",
      "sec-ch-ua-mobile": "?0",
      "sec-ch-ua-platform": "Windows"
    },
    "page_header": {
      "Host": "baijiahao.baidu.com",
      "User-Agent": "Mozilla/5.0 (Windows NT 10.0; Win64; x64) AppleWebKit/537.36 (KHTML, like Gecko) Chrome/92.0.4515.131 Safari/537.36",
      "Accept": "text/html,application/xhtml+xml,application/xml;q=0.9,image/avif,image/webp,image/apng,*/*;q=0.8,application/signed-exchange;v=b3;q=0.9",
      "Accept-Language": "zh,en-GB;q=0.9,en-US;q=0.8,en;q=0.7",
      "Accept-Encoding": "gzip, deflate, br",
      "Connection": "keep-alive",
      "Upgrade-Insecure-Requests": "1",
      "Sec-Fetch-Dest": "document",
      "Sec-Fetch-Mode": "navigate",
      "Sec-Fetch-Site": "none",
      "Sec-Fetch-User": "?1",
      "Cache-Control": "max-age=0"
    },
    "comment_header": {
      "Host": "ext.baidu.com",
      "User-Agent": "Mozilla/5.0 (Windows NT 10.0; Win64; x64) AppleWebKit/537.36 (KHTML, like Gecko) Chrome/92.0.4515.131 Safari/537.36",
      "Accept": "*/*",
      "Accept-Language": "zh,en-GB;q=0.9,en-US;q=0.8,en;q=0.7",
      "Accept-Encoding": "gzip, deflate, br",
      "Connection": "keep-alive",
      "Upgrade-Insecure-Requests": "1",
      "Sec-Fetch-Dest": "script",
      "Sec-Fetch-Mode": "no-cors",
      "Sec-Fetch-Site": "same-site",
      "Sec-Fetch-User": "?1",
      "Cache-Control": "max-age=0"
    },
    "hot_url": "",
    "content_url": "None",
    "search_url": "https://www.baidu.com/s?ie=utf-8&medium=2&rtt=1&bsst=1&rsv_dl=news_b_pn&cl=2&wd=$keyword&tn=news&rsv_bp=1&oq=&rsv_btype=t&f=8&x_bfe_rqs=03208&x_bfe_tjscore=0.080000&tngroupname=organic_news&newVideo=12&goods_entry_switch=1&pn=$page"
  },
  "豆瓣1": {
    "header": {
      "Connection": "keep-alive",
      "Cache-Control": "max-age=0",
      "sec-ch-ua": "'Chromium';v='92', ' Not A;Brand';v='99', 'Google Chrome';v='92'",
      "sec-ch-ua-mobile": ",?0",
      "Upgrade-Insecure-Requests": "1",
      "User-Agent": "Mozilla/5.0 (Windows NT 10.0; Win64; x64) AppleWebKit/537.36 (KHTML, like Gecko) Chrome/92.0.4515.131 Safari/537.36",
      "Accept": "text/html,application/xhtml+xml,application/xml;q=0.9,image/avif,image/webp,image/apng,*/*;q=0.8,application/signed-exchange;v=b3;q=0.9",
      "Sec-Fetch-Site": "same-origin",
      "Sec-Fetch-Mode": "navigate",
      "Sec-Fetch-User": "?1",
      "Sec-Fetch-Dest": "document",
      "Referer": "https://movie.douban.com/",
      "Accept-Language": "zh,en-GB;q=0.9,en-US;q=0.8,en;q=0.7,zh-CN;q=0.6"
    },
    "hot_url": ""
  },
  "复兴网": {
    "header": {
      "Connection": "keep-alive",
      "Cache-Control": "max-age=0",
      "Upgrade-Insecure-Requests": "1",
      "User-Agent": "Mozilla/5.0 (X11; Linux x86_64) AppleWebKit/537.36 (KHTML, like Gecko) Chrome/93.0.4577.63 Safari/537.36",
      "Accept": "text/html,application/xhtml+xml,application/xml;q=0.9,image/avif,image/webp,image/apng,*/*;q=0.8,application/signed-exchange;v=b3;q=0.9",
      "Referer": "https://www.baidu.com/link?url=m8DZ7QudRoRhnB_tdKkbOIgCnschfR5QNmof-xV1BRe&wd=&eqid=ffbbf0e1000ac36600000003616cd8ce",
      "Accept-Language": "zh-CN,zh;q=0.9",
      "If-None-Match": "'616cd717-12535'",
      "If-Modified-Since": "Mon, 18 Oct 2021 02:08:23 GMT"
    },
    "hot_url": "",
    "search_url": "https://www.mzfxw.com/"
  },
  "环球网": {
    "header": {
      "authority": "www.huanqiu.com",
      "cache-control": "max-age=0",
      "sec-ch-ua": "'Chromium';v='94', 'Google Chrome';v='94', ';Not A Brand';v='99'",
      "sec-ch-ua-mobile": "?0",
      "sec-ch-ua-platform": "'Windows'",
      "upgrade-insecure-requests": "1",
      "user-agent": "Mozilla/5.0 (Windows NT 10.0; Win64; x64) AppleWebKit/537.36 (KHTML, like Gecko) Chrome/94.0.4606.81 Safari/537.36",
      "accept": "text/html,application/xhtml+xml,application/xml;q=0.9,image/avif,image/webp,image/apng,*/*;q=0.8,application/signed-exchange;v=b3;q=0.9",
      "sec-fetch-site": "none",
      "sec-fetch-mode": "navigate",
      "sec-fetch-user": "?1",
      "sec-fetch-dest": "document",
      "accept-language": "zh-CN,zh;q=0.9",
      "cookie": "REPORT_UID_=CjodCqFD3LtKf7uuQ5cRNZrJYK0gTKMd; UM_distinctid=17c157cdb891af-0a2608eaa0b2c8-a7d173c-1fa400-17c157cdb8a574; _ma_tk=haf2xadtlyczelwjydrey76pnqrt1q7y; _ma_starttm=1634301033533; _ma_is_new_u=0; Hm_lvt_1fc983b4c305d209e7e05d96e713939f=1632448077,1632464248,1632646057,1634301034; CNZZDATA1000010102=1237754809-1632441932-https%253A%252F%252Fwww.baidu.com%252F%7C1634365484; Hm_lpvt_1fc983b4c305d209e7e05d96e713939f=1634369707",
      "if-modified-since": "Sat, 16 Oct 2021 07:35:03 GMT"
    },
    "search_url": "https://www.huanqiu.com/",
    "content_url": "None"
  },
  "hot_url": "",
  "凤凰网": {
    "header": {
      "Connection": "keep-alive",
      "Cache-Control": "max-age=0",
      "sec-ch-ua": "'Chromium';v='94', 'Google Chrome';v='94', ';Not A Brand';v='99'",
      "sec-ch-ua-mobile": "?0",
      "sec-ch-ua-platform": "'Windows'",
      "Upgrade-Insecure-Requests": "1",
      "User-Agent": "Mozilla/5.0 (Windows NT 10.0; Win64; x64) AppleWebKit/537.36 (KHTML, like Gecko) Chrome/94.0.4606.81 Safari/537.36",
      "Accept": "text/html,application/xhtml+xml,application/xml;q=0.9,image/avif,image/webp,image/apng,*/*;q=0.8,application/signed-exchange;v=b3;q=0.9",
      "Sec-Fetch-Site": "same-site",
      "Sec-Fetch-Mode": "navigate",
      "Sec-Fetch-User": "?1",
      "Sec-Fetch-Dest": "document",
      "Referer": "https://www.ifeng.com/",
      "Accept-Language": "zh-CN,zh;q=0.9",
      "cookie": "prov=cn0531; if_prov=cn0531; city=0532; if_city=0532; weather_city=sd_qd; userid=1632446830545_srzke76177; UM_distinctid=17c156a025b422-030e33b0e1536a-a7d173c-1fa400-17c156a025c839; region_ver=1.2; region_ip=124.129.172.x"
    },
    "hot_url": "https://www.ifeng.com/",
    "search_url": "https://shankapi.ifeng.com/season/getSoFengData/slide/$keyword/$page/getSoFengDataCallback?callback=getSoFengDataCallback&_="
  },
  "联合早报": {
    "header": {
      "authority": "www.zaobao.com",
      "cache-control": "max-age=0",
      "sec-ch-ua": "'Chromium';v='92', ' Not A;Brand';v='99', 'Google Chrome';v='92'",
      "sec-ch-ua-mobile": "?0",
      "upgrade-insecure-requests": "1",
      "user-agent": "Mozilla/5.0 (Windows NT 10.0; Win64; x64) AppleWebKit/537.36 (KHTML, like Gecko) Chrome/92.0.4515.131 Safari/537.36",
      "accept": "text/html,application/xhtml+xml,application/xml;q=0.9,image/avif,image/webp,image/apng,*/*;q=0.8,application/signed-exchange;v=b3;q=0.9",
      "sec-fetch-site": "same-origin",
      "sec-fetch-mode": "navigate",
      "sec-fetch-user": "?1",
      "sec-fetch-dest": "document",
      "referer": "https://www.zaobao.com/",
      "accept-language": "zh,en-GB;q=0.9,en-US;q=0.8,en;q=0.7,zh-CN;q=0.6",
      "cookie": "UM_distinctid=17c81f016777e8-09b9909956df2d-4343363-144000-17c81f0167840b; Hm_lvt_94444c9ea980451456647b253e40ad9f=1634267568; _ga=GA1.2.1942067935.1634267568; _gid=GA1.2.597843575.1634267568; CNZZDATA1279902962=198764089-1634261801-https%253A%252F%252Fwww.baidu.com%252F%7C1634262274; __gads=ID=13f6f9f94e7cc078:T=1634267549:S=ALNI_MagGNcN1eN6ZX_3q3o9p5l2uKktfw; suid=67b584f18c404d46bf139620de547f1d; sessionStatusZB=1; _hjid=4b9fc49c-77a3-4d6d-952a-cde4ed6b8769; Hm_lpvt_94444c9ea980451456647b253e40ad9f=1634280146; _dc_gtm_UA-41227313-8=1",
      "if-modified-since": "Fri, 15 Oct 2021 06:34:46 GMT"
    },
    "hot_url": "",
    "search_url": "https://www.zaobao.com/search?pageNo=$page&pageSize=10&keywords=$keyword"
  },
  "人民网": {
    "header": {
      "Accept": "application/json, text/plain, */*",
      "Accept-Language": "zh-CN,zh;q=0.9",
      "Connection": "keep-alive",
      "Origin": "http://search.people.cn",
      "Referer": "http://search.people.cn/s/?keyword=%E6%8A%97%E7%96%AB&st=0&_=1652337831597",
      "User-Agent": "Mozilla/5.0 (Windows NT 10.0; Win64; x64) AppleWebKit/537.36 (KHTML, like Gecko) Chrome/101.0.4951.54 Safari/537.36"
    },
    "hot_url": "",
    "search_url": "http://search.people.cn/search-platform/front/search",
    "content_url": "123"
  },
  "人民日报": {
    "header": {
      "Proxy-Connection": "keep-alive",
      "Cache-Control": "max-age=0",
      "Upgrade-Insecure-Requests": "1",
      "User-Agent": "Mozilla/5.0 (Windows NT 10.0; Win64; x64) AppleWebKit/537.36 (KHTML, like Gecko) Chrome/94.0.4606.81 Safari/537.36",
      "Accept": "text/html,application/xhtml+xml,application/xml;q=0.9,image/avif,image/webp,image/apng,*/*;q=0.8,application/signed-exchange;v=b3;q=0.9",
      "Accept-Language": "zh-CN,zh;q=0.9",
      "If-None-Match": "'6169e6c7-892f'",
      "If-Modified-Since": "Fri, 15 Oct 2021 20:38:31 GMT"
    },
    "hot_url": "",
    "search_url": "http://paper.people.com.cn/rmrb/html/$date/",
    "content_url": "123"
  },
  "强国论坛": {
    "header": {
      "Connection": "keep-alive",
      "Cache-Control": "max-age=0",
      "Upgrade-Insecure-Requests": "1",
      "User-Agent": "Mozilla/5.0 (X11; Linux x86_64) AppleWebKit/537.36 (KHTML, like Gecko) Chrome/93.0.4577.63 Safari/537.36",
      "Accept": "text/html,application/xhtml+xml,application/xml;q=0.9,image/avif,image/webp,image/apng,*/*;q=0.8,application/signed-exchange;v=b3;q=0.9",
      "Referer": "https://www.baidu.com/link?url=Roe-owpTn1HCV_NWcaGiP3dXZxzZtF15_VEYRV-Za2nWpqjxvJNhCBvke0hNmLDD&wd=&eqid=c4072dc900063ecc00000003616cec6f",
      "Accept-Language": "zh-CN,zh;q=0.9"
    },
    "hot_url": "",
    "search_url": "http://bbs1.people.com.cn/board/1.html",
    "content_url": "http://bbs1.people.com.cn/content_sync.do?postId=$url_num"
  },
  "求是": {
    "header": {
      "Connection": "keep-alive",
      "Cache-Control": "max-age=0",
      "Upgrade-Insecure-Requests": "1",
      "User-Agent": "Mozilla/5.0 (Windows NT 10.0; Win64; x64) AppleWebKit/537.36 (KHTML, like Gecko) Chrome/92.0.4515.131 Safari/537.36",
      "Accept": "text/html,application/xhtml+xml,application/xml;q=0.9,image/avif,image/webp,image/apng,*/*;q=0.8,application/signed-exchange;v=b3;q=0.9",
      "Accept-Language": "zh,en-GB;q=0.9,en-US;q=0.8,en;q=0.7,zh-CN;q=0.6",
      "If-Modified-Since": "Tue, 07 Sep 2021 07:24:05 GMT"
    },
    "hot_url": "",
    "search_url": "http://so.news.cn/qiushi/more?callback=jsonpCallback&page=$page&keyword=$keyword&searchword=(LinkTitle%3D%E5%AD%9F%E6%99%9A%E8%88%9F+or+IntroTitle%3D%E5%AD%9F%E6%99%9A%E8%88%9F+or+SubTitle%3D%E5%AD%9F%E6%99%9A%E8%88%9F)+AND+PubTime+%3E%3D%272020.10.15%27&orderby=RELEVANCE&_=1634290554883",
    "content_url": "123"
  },
  "搜狗": {
    "header": {
      "Connection": "keep-alive",
      "sec-ch-ua": "'Chromium';v='94', 'Google Chrome';v='94', ';Not A Brand';v='99'",
      "sec-ch-ua-mobile": "?0",
      "User-Agent": "Mozilla/5.0 (Windows NT 10.0; Win64; x64) AppleWebKit/537.36 (KHTML, like Gecko) Chrome/94.0.4606.81 Safari/537.36",
      "sec-ch-ua-platform": "'Windows'",
      "Accept": "image/avif,image/webp,image/apng,image/svg+xml,image/*,*/*;q=0.8",
      "Sec-Fetch-Site": "same-site",
      "Sec-Fetch-Mode": "no-cors",
      "Sec-Fetch-Dest": "image",
      "Referer": "https://top.sogou.com/",
      "Accept-Language": "zh-CN,zh;q=0.9"
    },
    "hot_url": "https://news.sogou.com/mil.shtml"
  },
  "贴吧": {
    "header": {
      "Connection": "keep-alive",
      "sec-ch-ua": "'Chromium';v='92',' Not A;Brand';v='99', 'Google Chrome';v='92'",
      "sec-ch-ua-mobile": "?0",
      "Upgrade-Insecure-Requests": "1",
      "User-Agent": "Mozilla/5.0 (Windows NT 10.0; Win64; x64) AppleWebKit/537.36 (KHTML, like Gecko) Chrome/92.0.4515.131 Safari/537.36",
      "Accept": "text/html,application/xhtml+xml,application/xml;q=0.9,image/avif,image/webp,image/apng,*/*;q=0.8,application/signed-exchange;v=b3;q=0.9",
      "Sec-Fetch-Site": "same-origin",
      "Sec-Fetch-Mode": "navigate",
      "Sec-Fetch-User": "?1",
      "Sec-Fetch-Dest": "document",
      "Referer": "https://tieba.baidu.com/f/search/res?ie=utf-8&qw=%E7%83%88%E5%A3%AB%E7%BA%AA%E5%BF%B5%E6%97%A5",
      "Accept-Language": "zh,en-GB;q=0.9,en-US;q=0.8,en;q=0.7,zh-CN;q=0.6"
    },
    "hot_url": "https://www.baidu.com/s?ie=utf-8&medium=0&rtt=4&bsst=1&rsv_dl=news_t_sk&cl=2&wd=$keyword&tn=news&rsv_bp=1&tfflag=0",
    "search_url": "https://tieba.baidu.com/f/search/res?isnew=1&kw=&qw=$qw&rn=10&un=&only_thread=0&sm=1&sd=&ed=&pn=$pn"
  },
  "铁血网": {
    "header": {
      "Connection": "keep-alive",
      "Cache-Control": "max-age=0",
      "sec-ch-ua": "'Google Chrome';v='93', ' Not;A Brand';v='99', 'Chromium';v='93'",
      "sec-ch-ua-mobile": "?0",
      "sec-ch-ua-platform": "'Linux'",
      "Upgrade-Insecure-Requests": "1",
      "User-Agent": "Mozilla/5.0 (X11; Linux x86_64) AppleWebKit/537.36 (KHTML, like Gecko) Chrome/93.0.4577.63 Safari/537.36",
      "Accept": "text/html,application/xhtml+xml,application/xml;q=0.9,image/avif,image/webp,image/apng,*/*;q=0.8,application/signed-exchange;v=b3;q=0.9",
      "Sec-Fetch-Site": "cross-site",
      "Sec-Fetch-Mode": "navigate",
      "Sec-Fetch-User": "?1",
      "Sec-Fetch-Dest": "document",
      "Referer": "https://www.baidu.com/link?url=cBIpLDY_0PHQ2B2TB7S8v7taW_HP8sS8O-ozob5LUy58-UvNctD6CKJxTzVM0vHO&wd=&eqid=e26225fa00003aef0000000361692445",
      "Accept-Language": "zh-CN,zh;q=0.9",
      "If-None-Match": "W/'6296b53290c1d71:0'",
      "If-Modified-Since": "Fri, 15 Oct 2021 06:45:10 GMT"
    },
    "hot_url": ""
  },
  "头条": {
    "header": {
      "Connection": "keep-alive",
      "Cache-Control": "max-age=0",
      "sec-ch-ua": "'Chromium';v='92', ' Not A;Brand';v='99', 'Google Chrome';v='92'",
      "sec-ch-ua-mobile": "?0",
      "Upgrade-Insecure-Requests": "1",
      "User-Agent": "Mozilla/5.0 (Windows NT 10.0; Win64; x64) AppleWebKit/537.36 (KHTML, like Gecko) Chrome/92.0.4515.131 Safari/537.36",
      "Accept": "text/html,application/xhtml+xml,application/xml;q=0.9,image/avif,image/webp,image/apng,*/*;q=0.8,application/signed-exchange;v=b3;q=0.9",
      "Sec-Fetch-Site": "none",
      "Sec-Fetch-Mode": "navigate",
      "Sec-Fetch-User": "?1",
      "Sec-Fetch-Dest": "document",
      "Accept-Language": "zh,en-GB;q=0.9,en-US;q=0.8,en;q=0.7"
    },
    "hot_url": "",
    "search_url": "https://so.toutiao.com/search?keyword=$keyword&pd=synthesis&source=pagination&dvpf=pc&aid=4916&page_num=$page&search_id=2021100715304401015013503047912E3D&filter_vendor=site&index_resource=site&filter_period=all&min_time=0&max_time=1633591574",
    "content_url": "123"
  },
  "乌有之乡": {
    "header": {
      "Upgrade-Insecure-Requests": "1",
      "User-Agent": "Mozilla/5.0 (Windows NT 10.0; Win64; x64) AppleWebKit/537.36 (KHTML, like Gecko) Chrome/94.0.4606.81 Safari/537.36",
      "Referer": "http://www.wyzxwk.com/"
    },
    "hot_url": "",
    "search_url": "http://www.wyzxwk.com/article/ualist/index.html",
    "content_url": "123"
  },
  "微博": {
    "header": {
      "authority": "rm.api.weibo.com",
      "method": "GET",
      "path": "/2/remind/push_count.json?trim_null=1&with_dm_group=1&with_reminding=1&with_settings=1&exclude_attitude=1&with_chat_group_notice=1&source=2936099636&with_chat_group=1&with_dm_unread=1&callback=__jp3",
      "scheme": "https",
      "accept": "*/*",
      "accept-encoding": "gzip, deflate, br",
      "accept-language": "zh-CN,zh;q=0.9",
      "cookie": "SINAGLOBAL=8115020293746.391.1618406050268; UOR=,,www.baidu.com; SCF=AnWUJToMzNT-9SrDk496VP7ajl-dlV2iHUODDHPbNPc3Fhrf3d0SLNXSvAw3c5T4m2M_Ln1UnJIeu7JeoOgOZo4.; login_sid_t=4779197d25a49d224c35e3955ab1dd2d; cross_origin_proto=SSL; _s_tentry=-; Apache=543801126887.1068.1656639745422; ULV=1656639745426:37:1:1:543801126887.1068.1656639745422:1654687403741; SUBP=0033WrSXqPxfM725Ws9jqgMF55529P9D9Wh7KBKaeHAZnm-HHBzVH5H-5JpX5o275NHD95QNS05NS0nc1hzNWs4Dqcjqi--fiKnci-8hi--fiKnfi-i2P0ecShnf; SSOLoginState=1656658133; SUB=_2A25PuuiFDeRhGeFJ61UW-CjEyTuIHXVszl1NrDV8PUNbmtB-LWLfkW9NfLnItjaFsiWAXrk7FX9QIlQ6if_TbrJO; ALF=1688194132",
      "referer": "https://s.weibo.com/",
      "sec-ch-ua": "'.Not/A)Brand';v='99', 'Google Chrome';v='103', 'Chromium';v='103'",
      "sec-ch-ua-mobile": "?0",
      "sec-ch-ua-platform": "Windows",
      "sec-fetch-dest": "script",
      "sec-fetch-mode": "no-cors",
      "sec-fetch-site": "same-site",
      "user-agent": "Mozilla/5.0 (Windows NT 10.0; Win64; x64) AppleWebKit/537.36 (KHTML, like Gecko) Chrome/103.0.0.0 Safari/537.36"
    },
    "hot_url": "https://weibo.com/ajax/side/hotSearch",
    "search_url2": "https://weibo.com/ajax/search/all?containerid=100103type%3D1%26q%3D$keyword%26t%3D0&page=$page&count=20",
    "search_url": "https://s.weibo.com/weibo?q=$keyword&page=$page",
    "content_url": "https://weibo.com/ajax/statuses/show?id=$weibo_id",
    "like_url": "https://weibo.com/ajax/statuses/likeShow?id=$uid&attitude_type=0&attitude_enable=1&page=$page&count=20",
    "comment0_url": "https://weibo.com/ajax/statuses/buildComments?is_reload=1&id=$mid&is_show_bulletin=2&is_mix=0&count=20&uid=$uid",
    "comment1_url": "https://weibo.com/ajax/statuses/buildComments?flow=0&is_reload=1&id=$mid&is_show_bulletin=2&is_mix=0&max_id=$max_id&count=20&uid=$uid",
    "user_url": "https://weibo.com/ajax/profile/info?uid=$uid",
    "repost_url": "https://weibo.com/ajax/statuses/repostTimeline?id=$mid&page=$page&moduleID=feed"
  },
  "微博用户": {
    "header": {
      "accept": "application/json, text/plain, */*",
      "accept-encoding": "gzip, deflate, br",
      "accept-language": "zh-CN,zh;q=0.9",
      "cookie": "'SINAGLOBAL=9799284069437.23.1632574449347; UOR=,,www.baidu.com; SUBP=0033WrSXqPxfM725Ws9jqgMF55529P9D9Wh7KBKaeHAZnm-HHBzVH5H-5JpX5KMhUgL.FoMNehMN1hqReoM2dJLoIpnLxK-L1hqLB-eLxK-L1h-LB.xke0qX1h-t; ALF=1665887894; SSOLoginState=1634351894; SCF=AuNgJvnLTVwnuZ9uO6iasjhdOpM7dKqO-Fp-JtPuPjkIl3JJgm8lFpdbPzyz-3A-8ok-HKIIHcbQ9vKm3Lq1BC4.; SUB=_2A25MbktGDeRhGeFJ61UW-CjEyTuIHXVvGjuOrDV8PUNbmtAKLVfVkW9NfLnItoBnGttYi6N8il5PPhamGaQ6otJn; XSRF-TOKEN=CJRQ5TGUYQRjppJVpSKq1I0D; WBPSESS=OvqoS8Zk4JL50oaa6BV2KzRrB0l2ZoeAF9CuApqPBTqYOni_ExGC8agpRAbhi_X8D8O96byWiZc7cM6WyMj3gbgRAOCUNvObl2FKPnZ-T6kZ7ldYspsrTlgeHDhdlgkA; _s_tentry=weibo.com; Apache=2044028948218.3726.1634352021749; ULV=1634352021780:15:10:5:2044028948218.3726.1634352021749:1634125056691'",
      "sec-ch-ua": "\"Google Chrome\";v=\"93\", \" Not;A Brand\";v=\"99\", \"Chromium\";v=\"93\"",
      "sec-ch-ua-mobile": "?0",
      "sec-ch-ua-platform": "\"Linux\"",
      "sec-fetch-dest": "empty",
      "sec-fetch-mode": "cors",
      "sec-fetch-site": "same-origin",
      "traceparent": "00-39d0fa273a05b60f3e91ad85ffa0fcc0-b3b5744face2fcff-00",
      "user-agent": "Mozilla/5.0 (X11; Linux x86_64) AppleWebKit/537.36 (KHTML, like Gecko) Chrome/93.0.4577.63 Safari/537.36",
      "x-requested-with": "XMLHttpRequest",
      "x-xsrf-token": "8-sppY1kKRpY2ifthSuvTEe_"
    },
    "follows_url": "https://weibo.com/ajax/friendships/friends?page=$page&uid=$uid",
    "fans_url": "https://weibo.com/ajax/friendships/friends?relate=fans&page=$page&uid=$uid&type=fans&newFollowerCount=0",
    "user_history_url": "https://weibo.com/ajax/statuses/mymblog?uid=$uid&page=$page&feature=0",
    "user_detail_url": "https://weibo.com/ajax/profile/detail?uid=$uid",
    "user_url": "https://weibo.com/ajax/profile/info?uid=$uid"
  },
  "微信": {
    "header": {
      "Connection": "keep-alive",
      "Cache-Control": "max-age=0",
      "sec-ch-ua": "'Chromium';v='92', ' Not A;Brand';v='99', 'Google Chrome';v='92'",
      "sec-ch-ua-mobile": "?0",
      "Upgrade-Insecure-Requests": "1",
      "User-Agent": "Mozilla/5.0 (Windows NT 10.0; Win64; x64) AppleWebKit/537.36 (KHTML, like Gecko) Chrome/92.0.4515.131 Safari/537.36",
      "Accept": "text/html,application/xhtml+xml,application/xml;q=0.9,image/avif,image/webp,image/apng,*/*;q=0.8,application/signed-exchange;v=b3;q=0.9",
      "Sec-Fetch-Site": "same-origin",
      "Sec-Fetch-Mode": "navigate",
      "Sec-Fetch-User": "?1",
      "Sec-Fetch-Dest": "document",
      "Accept-Language": "zh,en-GB;q=0.9,en-US;q=0.8,en;q=0.7"
    },
    "hot_url": "",
    "search_url": "https://weixin.sogou.com/weixin?query=$keyword&s_from=hotnews&type=2&page=$page&ie=utf8",
    "content_url": "111"
  },
  "西陆军事": {
    "header": {
      "Connection": "keep-alive",
      "Cache-Control": "max-age=0",
      "Upgrade-Insecure-Requests": "1",
      "User-Agent": "Mozilla/5.0 (X11; Linux x86_64) AppleWebKit/537.36 (KHTML, like Gecko) Chrome/93.0.4577.63 Safari/537.36",
      "Accept": "text/html,application/xhtml+xml,application/xml;q=0.9,image/avif,image/webp,image/apng,*/*;q=0.8,application/signed-exchange;v=b3;q=0.9",
      "Referer": "https://www.baidu.com/link?url=ImagoC3DE1p0D55S7qbzXrjJ3sGeO3nC9BwzL8q75Wtil8_pJOWqeNA2dRgp8r3n&wd=&eqid=f4b4737e0001ccbe0000000361693525",
      "Accept-Language": "zh-CN,zh;q=0.9"
    },
    "hot_url": "",
    "search_url": "http://junshi.xilu.com/"
  },
  "炎黄春秋": {
    "header": {
      "Accept": "text/javascript, application/javascript, application/ecmascript, application/x-ecmascript, */*; q=0.01",
      "Accept-Encoding": "gzip, deflate",
      "Accept-Language": "zh-CN,zh;q=0.9",
      "Connection": "keep-alive",
      "Cookie": "_pk_id.5.9039=64bd127280097a81.1650339234.; _pk_ses.5.9039=1",
      "Host": "www.yhcqw.com",
      "Referer": "http://www.yhcqw.com/97/97_1.html?hid=%E5%AD%9F%E6%99%9A%E8%88%9F",
      "User-Agent": "Mozilla/5.0 (Windows NT 10.0; Win64; x64) AppleWebKit/537.36 (KHTML, like Gecko) Chrome/100.0.4896.88 Safari/537.36",
      "X-Requested-With": "XMLHttpRequest"
    },
    "hot_url": "",
    "search_url": "http://www.yhcqw.com/cms/content/fullSearchList?jsonpCallback=jQuery111104702743438657311_1634108383319&page=1&rows=1000000&keyWord=$keyword&siteID=1&_=1634108383320",
    "content_url": "123"
  },
  "知乎": {
    "header": {
      "123": "123"
    },
    "hot_url": "",
    "search_url": "123",
    "content_url": "123"
  }
}
